{
  "db_name": "PostgreSQL",
  "query": "SELECT id, email, created_at, updated_at, language FROM users WHERE id = $1",
  "describe": {
    "columns": [
      {
        "ordinal": 0,
        "name": "id",
        "type_info": "Uuid"
      },
      {
        "ordinal": 1,
        "name": "email",
        "type_info": "Varchar"
      },
      {
        "ordinal": 2,
        "name": "created_at",
        "type_info": "Timestamp"
      },
      {
        "ordinal": 3,
        "name": "updated_at",
        "type_info": "Timestamp"
      },
      {
        "ordinal": 4,
        "name": "language",
        "type_info": "Varchar"
      }
    ],
    "parameters": {
      "Left": [
        "Uuid"
      ]
    },
    "nullable": [
      false,
      false,
      true,
      true,
      false
    ]
  },
  "hash": "8646a6aeabbdb2fd69acce527136b64828c9f4b7c316c76de1f7379f4aa0dc80"
}
